diskpack/__init__.py
diskpack/config.py
diskpack/geometry.py
diskpack/packer.py
diskpack-0.10.1.dist-info/LICENSE
diskpack-0.10.1.dist-info/METADATA
diskpack-0.10.1.dist-info/WHEEL
diskpack-0.10.1.dist-info/top_level.txt
diskpack-0.10.1.dist-info/RECORD
