Metadata-Version: 2.1
Name: diskpack
Version: 0.10.1
Summary: A high-performance vectorized circle packer with spatial hashing.
Author-email: James Kelly <mrkellyjam@gmail.com>
Requires-Python: >=3.8
License-File: LICENSE
Requires-Dist: numpy >=1.20
